[
    false,
    [
        [
            {"id": 91, "rsl": "6", "ru": "Хороший"},
            {"id": 1475, "rsl": "У", "ru": "Плохой"},
            {"id": 1737, "rsl": "ж", "ru": "Давать"},
            {"id": false, "rsl": "А", "ru": "Победить"}
        ],
        [
            {"id": 4943, "rsl": "6Е", "ru": "Гриб"},
            {"id": 4093, "rsl": "1э", "ru": "Слово"},
            {"id": 9040, "rsl": "оо", "ru": "Сложный"},
            {"id": 3789, "rsl": "65", "ru": "Вертолёт"},
            {"id": 970, "rsl": "22", "ru": "Кухня"},
            {"id": 899, "rsl": "33", "ru": "Огонь"},
            {"id": 646, "rsl": "58", "ru": "Восемь"},
            {"id": 4643, "rsl": "ва", "ru": "Печать"},
            {"id": 22516, "rsl": "вА", "ru": "Запирать"},
            {"id": 2883, "rsl": "5И", "ru": "Аллергия"}
        ]
    ],
    [
        [
            {"id": 6553, "rsl": "(Ё)1", "ru": "Индия"},
            {"id": 22440, "rsl": "(Ё)Р", "ru": "Болит голова"},
            {"id": 4947, "rsl": "(Ё)4", "ru": "Петух"}
        ],
        [
            {"id": 23755, "rsl": "(Й)1", "ru": "Близко"},
            {"id": 23091, "rsl": "(Й)о", "ru": "Германия"},
            {"id": 11684, "rsl": "(Й)Л", "ru": "Вонять"},
            {"id": false, "rsl": "(Й)5", "ru": "Юмор"}
        ],
        [
            {"id": 21652, "rsl": "(.)6", "ru": "Пробовать"},
            {"id": 5896, "rsl": "(.)о", "ru": "Ещё не"},
            {"id": 1767, "rsl": "(.)Л", "ru": "Смех"},
            {"id": 454, "rsl": "(.)5", "ru": "Время"}
        ]
    ],
    [
        [
            {"id": 9993, "rsl": "9Ё0в", "ru": "Давно"},
            {"id": false, "rsl": "9Ё07", "ru": "Грузовик"},
            {"id": 3437, "rsl": "у9Ё0у", "ru": "Рюкзак"}
        ],
        [
            {"id": 22555, "rsl": "9Й0в", "ru": "Мой"},
            {"id": 21535, "rsl": "9Й0Е", "ru": "Важно"},
            {"id": 499, "rsl": "9Й0а", "ru": "Злой"},
            {"id": 1480, "rsl": "И9Й0И", "ru": "Грустный"}
        ],
        [
            {"id": 2883, "rsl": "9.0И", "ru": "Аллергия"},
            {"id": 486, "rsl": "9.0ж", "ru": "Критиковать"},
            {"id": 199, "rsl": "ч9.0ч", "ru": "Чинить"},
            {"id": 21531, "rsl": "9.0о", "ru": "Проводить"}
        ]
    ],
    [
        [
            {"id": 4947, "rsl": "(Ё)*4", "ru": "Петух"},
            {"id": 11529, "rsl": "(Ё)Ц1", "ru": "Жара"},
            {"id": 22440, "rsl": "(Ё)+Р", "ru": "Болит голова"},
            {"id": 1034, "rsl": "(Й)*А", "ru": "Лук"},
            {"id": false, "rsl": "(Й)ЦЦу", "ru": "Невозможно"},
            {"id": 1767, "rsl": "(.)**Л", "ru": "Смех"},
            {"id": 1709, "rsl": "(.)Ц1", "ru": "Россия"},
            {"id": 1282, "rsl": "(.)+Ц*Ш", "ru": "Красивый"}
        ],
        [
            {"id": 3437, "rsl": "у*9Ё0*у", "ru": "Рюкзак"},
            {"id": false, "rsl": "вЦЦ9Ё0ЦЦв", "ru": "Здравствуйте"},
            {"id": 22555, "rsl": "9Й0*в", "ru": "Мой"},
            {"id": 21305, "rsl": "9Й0ЦЦ1", "ru": "Характер"},
            {"id": 8362, "rsl": "9.0***1", "ru": "Чувствовать"},
            {"id": 199, "rsl": "ч9.0ЦЦч", "ru": "Чинить"},
            {"id": 494, "rsl": "9.0Ц*э", "ru": "Очень"},
            {"id": 7908, "rsl": "9.0+о", "ru": "Проводить"}
        ],
        [
            {"id": 590, "rsl": "в*в", "ru": "Дом"},
            {"id": 1778, "rsl": "в*Н", "ru": "Путешествие"},
            {"id": 3924, "rsl": "в***6", "ru": "Участвовать"},
            {"id": 7826, "rsl": "ЛЦЛ", "ru": "Сломать"},
            {"id": 411, "rsl": "6ЦЦ1", "ru": "Имя"},
            {"id": 6853, "rsl": "вЦЦв", "ru": "Бесплатно"},
            {"id": 529, "rsl": "вЦЦж", "ru": "Запись"},
            {"id": 12127, "rsl": "С+С", "ru": "Дружба"},
            {"id": 7636, "rsl": "И+И", "ru": "Аппарат"},
            {"id": 3749, "rsl": "х+х", "ru": "Вирус"},
            {"id": 6987, "rsl": "Ш+ж", "ru": "Содержать"}
        ]
    ],
    {
        "Вверх": [
            {"id": 6025, "rsl": "6Ь", "ru": "Лучше"},
            {"id": 3904, "rsl": "вЦоЬ", "ru": "Выбрать"},
            {"id": 5896, "rsl": "(.)**оЬЬ", "ru": "Ещё не"},
            {"id": false, "rsl": "вЦ9Ё0ЦвЬЬ", "ru": "Здравствуйте"}
        ],
        "Вниз": [
            {"id": 3426, "rsl": "ЕЕ_", "ru": "Закон"},
            {"id": 7236, "rsl": "8__", "ru": "Тридцать"},
            {"id": 457, "rsl": "(.)1__", "ru": "Красный"},
            {"id": 1480, "rsl": "И*9Й0*И_", "ru": "Грустный"}
        ],
        "Влево": [
            {"id": 1513, "rsl": "оБ", "ru": "Часто"},
            {"id": 5733, "rsl": "6Б", "ru": "Неделя"},
            {"id": 23091, "rsl": "(Й)оББ", "ru": "Германия"},
            {"id": 1466, "rsl": "(.)*6Б", "ru": "Лень"}
        ],
        "Вправо": [
            {"id": 10030, "rsl": "5Ю", "ru": "Нет"},
            {"id": 1831, "rsl": "77Ю", "ru": "Готов"},
            {"id": 1709, "rsl": "(.)Ц1Ю", "ru": "Россия"},
            {"id": 9351, "rsl": "9Й0**НЮ", "ru": "Пыль"}
        ],
        "Вперёд": [
            {"id": 1475, "rsl": "У/", "ru": "Плохой"},
            {"id": 8074, "rsl": "в//", "ru": "Будущее"},
            {"id": 3916, "rsl": "(.)*о/", "ru": "Сказать"},
            {"id": 7908, "rsl": "9.0+о/", "ru": "Проводить"}
        ],
        "Назад": [
            {"id": 518, "rsl": "ввЗ", "ru": "Приглашать"},
            {"id": 4947, "rsl": "(Ё)*4ЗЗ", "ru": "Петух"},
            {"id": 22656, "rsl": "9Ё0вЗ", "ru": "Раньше"},
            {"id": 5940, "rsl": "9.0ЦНЗ", "ru": "Лысый"}
        ]
    },
    {
        "Примеры": [
            {"id": 199, "rsl": "чЭ.9.0ЦЦ.\"ч", "ru": "Чинить", "quizrslprompt": "ч9.0ЦЦч", "quizanswer": "Э..\""},
            {"id": 1767, "rsl": "(.)**\".Л", "ru": "Смех", "quizrslprompt": "(.)**Л", "quizanswer": "\"."},
            {"id": false, "rsl": "вЁ=Ц9Ё0Ц=Ёв", "ru": "Здравствуйте", "quizrslprompt": "вЦ9Ё0Цв", "quizanswer": "Ё==Ё"},
            {"id": 518, "rsl": "вЁ--ЁвЗ", "ru": "Приглашать", "quizrslprompt": "ввЗ", "quizanswer": "Ё--Ё"},
            {"id": 22440, "rsl": "(Ё)+=ЁР", "ru": "Болит голова", "quizrslprompt": "(Ё)+Р", "quizanswer": "=Ё"}
        ],
        "Не важна": [
            {
                "id": 648, "rsl": "еЭ.**.Эе", "ru": "Десять", "comment": "с ориентацией",
                "quizrslprompt": "е**е", "quizanswer": "Э..Э"
            },
            {"id": false, "rsl": "е**е", "ru": "Десять", "comment": "без ориентации", "noquiz": true},
            {
                "id": 5733, "rsl": "\".6Б", "ru": "Неделя", "comment": "с ориентацией",
                "quizrslprompt": "6Б", "quizanswer": "\"."
            },
            {"id": false, "rsl": "6Б", "ru": "Неделя", "comment": "без ориентации", "noquiz": true},
            {
                "id": 22555, "rsl": "9Й0*=Ёв", "ru": "Мой", "comment": "с ориентацией",
                "quizrslprompt": "9Й0*в", "quizanswer": "=Ё"},
            {"id": false, "rsl": "9Й0*в", "ru": "Мой", "comment": "без ориентации", "noquiz": true},
            {
                "id": 4947, "rsl": "(Ё)*.Э4ЗЗ", "ru": "Петух", "comment": "с ориентацией",
                "quizrslprompt": "(Ё)*4ЗЗ", "quizanswer": ".Э"
            },
            {"id": false, "rsl": "(Ё)*4ЗЗ", "ru": "Петух", "comment": "без ориентации", "noquiz": true}
        ],
        "Важна": [
            {"id": 1744, "rsl": "1Э.*.Э1", "ru": "Встреча", "quizrslprompt": "1*1", "quizanswer": "Э..Э"},
            {"id": 12114, "rsl": "1.=*=.1", "ru": "Точно", "quizrslprompt": "1*1", "quizanswer": ".==."},
            {"id": 8074, "rsl": ".Эв/", "ru": "Будет", "quizrslprompt": "в/", "quizanswer": ".Э"},
            {"id": 7399, "rsl": ".\"в/", "ru": "Тип", "quizrslprompt": "в/", "quizanswer": ".\""},
            {"id": 7574, "rsl": "9Й0**=.аЮ", "ru": "Алкоголик", "quizrslprompt": "9Й0**аЮ", "quizanswer": "=Ё"},
            {"id": 3189, "rsl": "9Й0**.ЭаЮ", "ru": "Терапевт", "quizrslprompt": "9Й0**аЮ", "quizanswer": ".Э"}
        ]
    }
]